llm_datasets/__init__.py
llm_datasets/__main__.py
llm_datasets/chunkify_datasets.py
llm_datasets/collect_metrics.py
llm_datasets/compose_dataset.py
llm_datasets/convert_parquet_to_jsonl.py
llm_datasets/extract_text.py
llm_datasets/hf_tokenize_parquet_dataset.py
llm_datasets/megatron_tokenize_parquet_dataset.py
llm_datasets/print_stats.py
llm_datasets/shuffle_datasets.py
llm_datasets/train_sp_tokenizer.py
llm_datasets/commands/__init__.py
llm_datasets/commands/chunkify_command.py
llm_datasets/commands/collect_metrics_command.py
llm_datasets/commands/compose_command.py
llm_datasets/commands/convert_parquet_to_jsonl_command.py
llm_datasets/commands/extract_text_command.py
llm_datasets/commands/hf_upload_command.py
llm_datasets/commands/print_stats_command.py
llm_datasets/commands/render_docs_command.py
llm_datasets/commands/shuffle_command.py
llm_datasets/commands/train_tokenizer_command.py
llm_datasets/datasets/__init__.py
llm_datasets/datasets/base.py
llm_datasets/datasets/dataset_registry.py
llm_datasets/datasets/hf_dataset.py
llm_datasets/datasets/jsonl_dataset.py
llm_datasets/datasets/parquet_dataset.py
llm_datasets/datasets/bg/__init__.py
llm_datasets/datasets/bg/bgnc_admin_eur.py
llm_datasets/datasets/bg/bgnc_news_corpus.py
llm_datasets/datasets/bg/bulgarian_news.py
llm_datasets/datasets/bg/bulnc.py
llm_datasets/datasets/code/__init__.py
llm_datasets/datasets/code/starcoder.py
llm_datasets/datasets/cs/__init__.py
llm_datasets/datasets/cs/cs_en_parallel.py
llm_datasets/datasets/cs/syn_v9.py
llm_datasets/datasets/da/__init__.py
llm_datasets/datasets/da/danewsroom.py
llm_datasets/datasets/da/danish_gigaword.py
llm_datasets/datasets/da/danish_parliament_corpus.py
llm_datasets/datasets/da/dk_clarin.py
llm_datasets/datasets/de/__init__.py
llm_datasets/datasets/de/de_laws.py
llm_datasets/datasets/de/dewac.py
llm_datasets/datasets/de/openlegaldata.py
llm_datasets/datasets/el/__init__.py
llm_datasets/datasets/el/greek_legal_code.py
llm_datasets-0.0.3.dist-info/LICENSE
llm_datasets-0.0.3.dist-info/METADATA
llm_datasets-0.0.3.dist-info/WHEEL
llm_datasets-0.0.3.dist-info/entry_points.txt
llm_datasets-0.0.3.dist-info/top_level.txt
llm_datasets-0.0.3.dist-info/RECORD
