Metadata-Version: 2.1
Name: llm-datasets
Version: 0.0.3
Summary: A collection of datasets for language model training including scripts for downloading, preprocesssing, and sampling.
Author-email: Malte Ostendorff <malte.ostendorff@dfki.de>
License: Apache 2.0
Project-URL: Documentation, https://github.com/malteos/llm-datasets/tree/main#readme
Project-URL: Source, https://github.com/malteos/llm-datasets
Project-URL: Tracker, https://github.com/malteos/llm-datasets/issues
Platform: UNKNOWN
Classifier: Development Status :: 3 - Alpha
Classifier: Intended Audience :: Developers
Classifier: License :: OSI Approved :: Apache Software License
Classifier: Programming Language :: Python :: 3 :: Only
Classifier: Programming Language :: Python :: 3.9
Classifier: Programming Language :: Python :: 3.10
Classifier: Programming Language :: Python :: 3.11
Requires-Python: >=3.9
License-File: LICENSE
Requires-Dist: requests
Requires-Dist: pandas
Requires-Dist: datasets
Requires-Dist: smart-open
Requires-Dist: wget
Requires-Dist: zstandard
Requires-Dist: polars
Requires-Dist: pyarrow >=14.0.1
Requires-Dist: dill
Provides-Extra: all
Requires-Dist: llm-datasets[datasets] ; extra == 'all'
Requires-Dist: llm-datasets[dev] ; extra == 'all'
Requires-Dist: llm-datasets[docs] ; extra == 'all'
Requires-Dist: llm-datasets[viewer] ; extra == 'all'
Provides-Extra: datasets
Requires-Dist: wget ==3.2 ; extra == 'datasets'
Requires-Dist: mwparserfromhell >=0.6.4 ; extra == 'datasets'
Requires-Dist: gensim >=4.3.0 ; extra == 'datasets'
Requires-Dist: zstandard >=0.20.0 ; extra == 'datasets'
Requires-Dist: treelib >=1.6.4 ; extra == 'datasets'
Requires-Dist: conllu >=4.5.3 ; extra == 'datasets'
Requires-Dist: prevert >=1.0.2 ; extra == 'datasets'
Requires-Dist: translate-toolkit >=3.9.1 ; extra == 'datasets'
Requires-Dist: folia >=2.5.8 ; extra == 'datasets'
Requires-Dist: estnltk >=1.7.1 ; extra == 'datasets'
Requires-Dist: Jinja2 ; extra == 'datasets'
Provides-Extra: dev
Requires-Dist: pre-commit ; extra == 'dev'
Requires-Dist: black ; extra == 'dev'
Requires-Dist: flake8 ; extra == 'dev'
Requires-Dist: flake8-pyproject ; extra == 'dev'
Requires-Dist: pytest ; extra == 'dev'
Requires-Dist: pytest-cov ; extra == 'dev'
Requires-Dist: pytest-runner ; extra == 'dev'
Requires-Dist: coverage ; extra == 'dev'
Requires-Dist: pylint ; extra == 'dev'
Requires-Dist: twine ; extra == 'dev'
Requires-Dist: jupyter ; extra == 'dev'
Provides-Extra: docs
Requires-Dist: mkdocs ; extra == 'docs'
Requires-Dist: mkdocs-material ; extra == 'docs'
Requires-Dist: mkdocs-exclude ; extra == 'docs'
Requires-Dist: mkdocstrings ; extra == 'docs'
Requires-Dist: mkdocstrings[python] ; extra == 'docs'
Provides-Extra: viewer
Requires-Dist: streamlit ; extra == 'viewer'
Requires-Dist: ngrok ; extra == 'viewer'
